verup/__init__.py
verup/main.py
verup-0.0.1.dist-info/LICENSE
verup-0.0.1.dist-info/METADATA
verup-0.0.1.dist-info/WHEEL
verup-0.0.1.dist-info/entry_points.txt
verup-0.0.1.dist-info/top_level.txt
verup-0.0.1.dist-info/RECORD
