Metadata-Version: 2.1
Name: verup
Version: 0.0.1
Summary: Version bumper for any package locally, pypi, github
Home-page: https://github.com/vishalvvr/verup
Author: Vishal Vijayraghavan
Author-email: vishalvvr@fedoraproject.org
License: GPLv3
Classifier: Operating System :: OS Independent
Classifier: Programming Language :: Python :: 3
Classifier: License :: OSI Approved :: GNU General Public License v3 (GPLv3)
License-File: LICENSE
Requires-Dist: requests
